snap_env
