Metadata-Version: 2.2
Name: snap-env
Version: 0.1.2
Summary: A sassy little env var loader
Home-page: https://github.com/mdigruber/snap-env
Author: Markus Digruber
Author-email: hello@markusdigruber.com
License: MIT
Dynamic: author
Dynamic: author-email
Dynamic: description
Dynamic: description-content-type
Dynamic: home-page
Dynamic: license
Dynamic: summary
